alteza/__init__.py
alteza/__main__.py
alteza/content.py
alteza/crawl.py
alteza/driver.py
alteza/fs.py
alteza/py.typed
alteza/util.py
alteza/version.py
alteza-1.0.3.dist-info/licenses/LICENSE
alteza-1.0.3.dist-info/METADATA
alteza-1.0.3.dist-info/WHEEL
alteza-1.0.3.dist-info/entry_points.txt
alteza-1.0.3.dist-info/top_level.txt
alteza-1.0.3.dist-info/RECORD
