Metadata-Version: 2.4
Name: alteza
Version: 1.0.3
Summary: Super-flexible Static Site Generator
Home-page: https://github.com/arjun-menon/alteza
Download-URL: https://github.com/arjun-menon/alteza/archive/v1.0.3.tar.gz
Author: Arjun G. Menon
Author-email: contact@arjungmenon.com
License: AGPL-3.0-or-later
Keywords: static site generator,static sites,ssg
Classifier: Development Status :: 4 - Beta
Classifier: Intended Audience :: Developers
Classifier: Topic :: Internet :: WWW/HTTP :: Dynamic Content
Classifier: Topic :: Internet :: WWW/HTTP :: Dynamic Content :: Content Management System
Classifier: Topic :: Internet :: WWW/HTTP :: Site Management
Classifier: Topic :: Software Development :: Libraries :: Python Modules
Classifier: Topic :: Text Processing :: Markup :: Markdown
Classifier: Topic :: Text Processing :: Markup :: HTML
Classifier: Operating System :: OS Independent
Classifier: Environment :: Console
Classifier: License :: OSI Approved :: GNU Affero General Public License v3
Requires-Python: >=3.10
License-File: LICENSE
Requires-Dist: pypage>=2.2.1
Requires-Dist: markdown>=3.6
Requires-Dist: mdx-breakless-lists>=1.0.1
Requires-Dist: mdx_truly_sane_lists>=1.3
Requires-Dist: pygments>=2.16.1
Requires-Dist: pyyaml>=6.0.1
Requires-Dist: colored>=2.2.4
Requires-Dist: sh>=2.0.7
Requires-Dist: typed-argument-parser>=1.10.1
Requires-Dist: watchdog>=4.0.1
Requires-Dist: tqdm>=4.67.1
Requires-Dist: pygit2>=1.16.2
Dynamic: author
Dynamic: author-email
Dynamic: classifier
Dynamic: description
Dynamic: description-content-type
Dynamic: download-url
Dynamic: home-page
Dynamic: keywords
Dynamic: license
Dynamic: license-file
Dynamic: requires-dist
Dynamic: requires-python
Dynamic: summary
